vai_toolkit/__init__.py
vai_toolkit/client.py
vai_toolkit/data.py
vai_toolkit/model.py
vai_toolkit/organization.py
vai_toolkit/pipeline.py
vai_toolkit/widget.py
vai_toolkit-0.0.11.dist-info/METADATA
vai_toolkit-0.0.11.dist-info/WHEEL
vai_toolkit-0.0.11.dist-info/licenses/LICENSE
vai_toolkit-0.0.11.dist-info/RECORD
