Metadata-Version: 2.1
Name: vai_toolkit
Version: 0.0.11
Summary: VAI toolkit, to add data in our platform
Author-email: VirtuousAI <info@virtuousai.com>
License: Copyright (c) 2018 The Python Packaging Authority
License-File: LICENSE
Classifier: License :: OSI Approved :: MIT License
Classifier: Operating System :: OS Independent
Classifier: Programming Language :: Python :: 3
Requires-Python: >=3.4
